LICENCE
README.md
setup.py
django_invoice.egg-info/PKG-INFO
django_invoice.egg-info/SOURCES.txt
django_invoice.egg-info/dependency_links.txt
django_invoice.egg-info/requires.txt
django_invoice.egg-info/top_level.txt
invoice/__init__.py
invoice/admin.py
invoice/context_processors.py
invoice/forms.py
invoice/models.py
invoice/pdf.py
invoice/tests.py
invoice/views.py
invoice/conf/__init__.py
invoice/conf/settings.py
invoice/management/__init__.py
invoice/management/commands/__init__.py
invoice/management/commands/send_invoices.py
invoice/migrations/0001_initial.py
invoice/migrations/0002_auto__del_field_invoice_due_date.py
invoice/migrations/0003_auto__add_field_invoice_invoiced.py
invoice/migrations/0004_status_info.py
invoice/migrations/0005_auto__del_field_invoice_status.py
invoice/migrations/0006_auto__add_field_invoice_draft.py
invoice/migrations/0007_auto__add_currency__add_field_invoice_currency.py
invoice/migrations/__init__.py
invoice/templates/admin/invoice/invoice/change_form.html
invoice/templates/invoice/invoice_email.txt
invoice/utils/__init__.py
invoice/utils/friendly_id.py